.VERSION
AUTHORS.rst
CONTRIBUTING.rst
HISTORY.rst
LICENSE
MANIFEST.in
Pipfile
Pipfile.lock
README.rst
USAGE.rst
dev-requirements.txt
requirements.txt
setup.cfg
setup.py
docs/Makefile
docs/authors.rst
docs/conf.py
docs/contributing.rst
docs/history.rst
docs/index.rst
docs/installation.rst
docs/readme.rst
docs/usage.rst
mqttcloudproviderslib/.VERSION
mqttcloudproviderslib/AUTHORS.rst
mqttcloudproviderslib/CONTRIBUTING.rst
mqttcloudproviderslib/HISTORY.rst
mqttcloudproviderslib/LICENSE
mqttcloudproviderslib/Pipfile
mqttcloudproviderslib/Pipfile.lock
mqttcloudproviderslib/README.rst
mqttcloudproviderslib/USAGE.rst
mqttcloudproviderslib/__init__.py
mqttcloudproviderslib/_version.py
mqttcloudproviderslib/dev-requirements.txt
mqttcloudproviderslib/mqttcloudproviderslib.py
mqttcloudproviderslib/mqttcloudproviderslibexceptions.py
mqttcloudproviderslib/requirements.txt
mqttcloudproviderslib/schemas.py
mqttcloudproviderslib.egg-info/PKG-INFO
mqttcloudproviderslib.egg-info/SOURCES.txt
mqttcloudproviderslib.egg-info/dependency_links.txt
mqttcloudproviderslib.egg-info/not-zip-safe
mqttcloudproviderslib.egg-info/requires.txt
mqttcloudproviderslib.egg-info/top_level.txt