Metadata-Version: 1.1
Name: mqttcloudproviderslib
Version: 0.1.6
Summary: A library implementing cloud provider authentication for AWS, Azure and Google cloud for use in mqtt messaging and implements a message hub to publish messages in a fan pattern to all providers.
Home-page: https://github.com/schubergphilis/mqttcloudproviderslib
Author: Costas Tyfoxylos
Author-email: ctyfoxylos@schubergphilis.com
License: MIT
Keywords: mqttcloudproviderslib paho mqtt azure aws gcp messaging
Platform: UNKNOWN
Classifier: Development Status :: 4 - Beta
Classifier: Intended Audience :: Developers
Classifier: License :: OSI Approved :: MIT License
Classifier: Natural Language :: English
Classifier: Programming Language :: Python :: 3.7
